ezdata/__init__.py
ezdata/_effort_error.py
ezdata/_entry.py
ezdata/_entry_log.py
ezdata/_ez_field.py
ezdata/_ez_meta.py
ezdata/_ez_namespace.py
utilities/__init__.py
utilities/_dict_field.py
utilities/_empty.py
utilities/_field.py
utilities/_list_field.py
utilities/_maybe.py
utilities/_mono_space.py
utilities/_plenty.py
utilities/_typed_field.py
ezdata-0.0.8.dist-info/LICENSE
ezdata-0.0.8.dist-info/METADATA
ezdata-0.0.8.dist-info/WHEEL
ezdata-0.0.8.dist-info/top_level.txt
ezdata-0.0.8.dist-info/RECORD
